0_orchestrator-1.1.0a8-py3.6-nspkg.pth
0_orchestrator-1.1.0a8.dist-info/DESCRIPTION.rst
0_orchestrator-1.1.0a8.dist-info/METADATA
0_orchestrator-1.1.0a8.dist-info/RECORD
0_orchestrator-1.1.0a8.dist-info/WHEEL
0_orchestrator-1.1.0a8.dist-info/metadata.json
0_orchestrator-1.1.0a8.dist-info/namespace_packages.txt
0_orchestrator-1.1.0a8.dist-info/top_level.txt
zeroos/orchestrator/__init__.py
zeroos/orchestrator/configuration.py
zeroos/orchestrator/client/Bridge.py
zeroos/orchestrator/client/BridgeCreate.py
zeroos/orchestrator/client/BridgeCreateSetting.py
zeroos/orchestrator/client/CPUInfo.py
zeroos/orchestrator/client/CPUStats.py
zeroos/orchestrator/client/CloudInit.py
zeroos/orchestrator/client/Cluster.py
zeroos/orchestrator/client/ClusterCreate.py
zeroos/orchestrator/client/Container.py
zeroos/orchestrator/client/ContainerListItem.py
zeroos/orchestrator/client/ContainerNIC.py
zeroos/orchestrator/client/ContainerNICconfig.py
zeroos/orchestrator/client/ContainerUpdate.py
zeroos/orchestrator/client/CoreStateResult.py
zeroos/orchestrator/client/CoreSystem.py
zeroos/orchestrator/client/CreateContainer.py
zeroos/orchestrator/client/CreateSnapshotReqBody.py
zeroos/orchestrator/client/DHCP.py
zeroos/orchestrator/client/Dashboard.py
zeroos/orchestrator/client/DashboardListItem.py
zeroos/orchestrator/client/DeleteFile.py
zeroos/orchestrator/client/DiskInfo.py
zeroos/orchestrator/client/DiskPartition.py
zeroos/orchestrator/client/EnumBridgeCreateNetworkMode.py
zeroos/orchestrator/client/EnumBridgeStatus.py
zeroos/orchestrator/client/EnumClusterCreateClusterType.py
zeroos/orchestrator/client/EnumClusterCreateDriveType.py
zeroos/orchestrator/client/EnumClusterCreateMetaDriveType.py
zeroos/orchestrator/client/EnumClusterCreateStorDriveType.py
zeroos/orchestrator/client/EnumClusterCreateStorMetaDriveType.py
zeroos/orchestrator/client/EnumClusterDriveType.py
zeroos/orchestrator/client/EnumClusterStatus.py
zeroos/orchestrator/client/EnumContainerListItemStatus.py
zeroos/orchestrator/client/EnumContainerNICStatus.py
zeroos/orchestrator/client/EnumContainerNICType.py
zeroos/orchestrator/client/EnumContainerStatus.py
zeroos/orchestrator/client/EnumDiskInfoType.py
zeroos/orchestrator/client/EnumGWNICType.py
zeroos/orchestrator/client/EnumGetGWStatus.py
