Metadata-Version: 2.0
Name: 0-orchestrator
Version: 1.1.0a8
Summary: Zero-OS Orchestrator
Home-page: https://github.com/g8os/grid
Author: Christophe de Carvalho
Author-email: christophe@gig.tech
License: Apache 2.0
Platform: UNKNOWN
Requires-Dist: Jinja2
Requires-Dist: aioredis
Requires-Dist: etcd3
Requires-Dist: netaddr
Requires-Dist: python-dateutil
